{
  "main": {
    "id": "73bb981c17c5376c",
    "type": "split",
    "children": [
      {
        "id": "401260a27986e5a6",
        "type": "tabs",
        "children": [
          {
            "id": "53b007133cb9a95e",
            "type": "leaf",
            "state": {
              "type": "markdown",
              "state": {
                "file": "Section14/207_Encrypted_Connections_with_SSL_TLS/207_Encrypted_Connections_with_SSL_TLS.md",
                "mode": "source",
                "source": false
              },
              "icon": "lucide-file",
              "title": "207_Encrypted_Connections_with_SSL_TLS"
            }
          }
        ]
      }
    ],
    "direction": "vertical"
  },
  "left": {
    "id": "a8a17e9057c43469",
    "type": "split",
    "children": [
      {
        "id": "eab8c8cdf806bfc7",
        "type": "tabs",
        "children": [
          {
            "id": "5d4d814af932e325",
            "type": "leaf",
            "state": {
              "type": "file-explorer",
              "state": {
                "sortOrder": "alphabetical"
              },
              "icon": "lucide-folder-closed",
              "title": "Files"
            }
          },
          {
            "id": "9b9cd54ac1fb7a7e",
            "type": "leaf",
            "state": {
              "type": "search",
              "state": {
                "query": "",
                "matchingCase": false,
                "explainSearch": false,
                "collapseAll": false,
                "extraContext": false,
                "sortOrder": "alphabetical"
              },
              "icon": "lucide-search",
              "title": "Search"
            }
          },
          {
            "id": "013c729b8909c5d4",
            "type": "leaf",
            "state": {
              "type": "bookmarks",
              "state": {},
              "icon": "lucide-bookmark",
              "title": "Bookmarks"
            }
          }
        ]
      }
    ],
    "direction": "horizontal",
    "width": 359.5
  },
  "right": {
    "id": "96a0b14a2389ab63",
    "type": "split",
    "children": [
      {
        "id": "1154b5ff2b34faf2",
        "type": "tabs",
        "children": [
          {
            "id": "c49fe2702a46cc7b",
            "type": "leaf",
            "state": {
              "type": "backlink",
              "state": {
                "collapseAll": false,
                "extraContext": false,
                "sortOrder": "alphabetical",
                "showSearch": false,
                "searchQuery": "",
                "backlinkCollapsed": false,
                "unlinkedCollapsed": true
              },
              "icon": "links-coming-in",
              "title": "Backlinks"
            }
          },
          {
            "id": "72b22557bb0abf38",
            "type": "leaf",
            "state": {
              "type": "outgoing-link",
              "state": {
                "linksCollapsed": false,
                "unlinkedCollapsed": true
              },
              "icon": "links-going-out",
              "title": "Outgoing links"
            }
          },
          {
            "id": "dbc55f56adbfb2e6",
            "type": "leaf",
            "state": {
              "type": "tag",
              "state": {
                "sortOrder": "frequency",
                "useHierarchy": true
              },
              "icon": "lucide-tags",
              "title": "Tags"
            }
          },
          {
            "id": "f5d2825db977c1e9",
            "type": "leaf",
            "state": {
              "type": "outline",
              "state": {},
              "icon": "lucide-list",
              "title": "Outline"
            }
          }
        ]
      }
    ],
    "direction": "horizontal",
    "width": 300,
    "collapsed": true
  },
  "left-ribbon": {
    "hiddenItems": {
      "switcher:Open quick switcher": false,
      "graph:Open graph view": false,
      "canvas:Create new canvas": false,
      "daily-notes:Open today's daily note": false,
      "templates:Insert template": false,
      "command-palette:Open command palette": false
    }
  },
  "active": "53b007133cb9a95e",
  "lastOpenFiles": [
    "Section14/216_OAuth_standard/216_The_OAuth_Standard.md",
    "Section14/217_OAuth_2_0_Code_Flow/217_OAuth_2_0_Code_Flow.md",
    "Section14/217_OAuth_2_0_Code_Flow/217_OAuth_2_0_Code_Flow",
    "Section14/217_OAuth_2_0_Code_Flow",
    "Section14/211_Helmet.js/211_Helmet.js.md",
    "Section14/215_JWT_Tokens/215_JWT_Tokens.md",
    "Section14/209_Setting_up_security_example/209_Security_Example.md",
    "Section14/207_Encrypted_Connections_with_SSL_TLS/207_Encrypted_Connections_with_SSL_TLS.md",
    "Section14/214_API_Keys/214_API_Keys.md",
    "Section14/216_OAuth_standard",
    "Section14/215_JWT_Tokens",
    "Section13/198_199_Paginating_our_Endpoints/199_Paginating_our_endpoints_2.md",
    "Section13/198_199_Paginating_our_Endpoints/198_Paginating_our_endpoints_1.md",
    "Section12/173_Object_ID/173_Object_IDs.md",
    "Section13/200_Sorting_paginated_data/200_Sorting_paginated_data.md",
    "Section13/197_Persisting_SpaceX_data/197_Persisting_SpaceX_launches.md",
    "Section13/195_Using_Paginated_APIs/195_Using_paginated_APIs.md",
    "Section13/196_Minimizing_API_load/196_Minimizing_API_load.md",
    "Section14/213_Social_Sign_In/213_Social_Sign_In.md",
    "Section14/214_API_Keys",
    "Section14/212_Authentication_Authorization/212_Authentication_Authorization.md",
    "Section14/213_Social_Sign_In",
    "Section14/212_Authentication_Authorization/Untitled",
    "Section14/212_Authentication_Authorization",
    "Section14/Security_Example/node_modules/helmet/index.d.mts",
    "Section14/Security_Example/node_modules/helmet/SECURITY.md",
    "Section14/Security_Example/node_modules/helmet/index.mjs",
    "Section14/Security_Example/node_modules/helmet/README.md",
    "Section14/Security_Example/node_modules/helmet/CHANGELOG.md",
    "Section14/210_HTTPS_Node/210_HTTPS_Node.md",
    "Section14/208_Digital_Certificates_MIM_attack_Signing/208_Digital_Certificates_MIM_attack_Signing.md",
    "Section14/Security_Example/node_modules/setprototypeof/README.md",
    "Section14/Security_Example/node_modules/mime-db/README.md",
    "Section14/Security_Example/node_modules/mime-db/HISTORY.md",
    "Section14/Security_Example/node_modules/media-typer/README.md",
    "Section14/Security_Example/node_modules/media-typer/HISTORY.md",
    "Section12/Untitled.canvas",
    "Section9/NASA_PROJECT/server/public/img/glow.png",
    "Section9/NASA_PROJECT/server/public/img/background.jpg",
    "Section9/NASA_PROJECT/server/public/img/background-medium.jpg",
    "Section9/NASA_PROJECT/server/public/img/background-large.jpg",
    "Section9/NASA_PROJECT/server/public/favicon.png",
    "Section9/NASA_PROJECT/client/build/img/glow.png",
    "Section9/NASA_PROJECT/client/build/img/background.jpg",
    "Section9/NASA_PROJECT/client/build/img/background-medium.jpg",
    "Section9/NASA_PROJECT/client/build/img/background-large.jpg",
    "Section9/NASA_PROJECT/client/build/favicon.png"
  ]
}